drf_extra_utils
