Metadata-Version: 2.1
Name: drf-extra-utils
Version: 1.0.3
Summary: Utils for django rest
Home-page: UNKNOWN
Author: Gabriel Lustosa
Author-email: lustosaki2@gmail.com
License: MIT License
Platform: UNKNOWN
Requires-Python: >=3.8
License-File: LICENSE
